get_case_data/__init__.py
get_case_data/funcs/__init__.py
get_case_data/funcs/apitools.py
get_case_data/funcs/auth.py
get_case_data/funcs/exceltools.py
get_case_data/main.py
get_case_data-0.1.2.dist-info/entry_points.txt
get_case_data-0.1.2.dist-info/METADATA
get_case_data-0.1.2.dist-info/WHEEL
get_case_data-0.1.2.dist-info/RECORD
